<?xml version="1.0" encoding="utf-8"?>
<TextureAtlas imagePath="Chained Marvin.png">
	<!-- Created with Adobe Animate version 24.0.3.19 -->
	<!-- http://www.adobe.com/products/animate.html -->
	<SubTexture name="Down0000" x="0" y="0" width="417" height="380" frameX="0" frameY="-62" frameWidth="417" frameHeight="446"/>
	<SubTexture name="Down0001" x="0" y="0" width="417" height="380" frameX="0" frameY="-62" frameWidth="417" frameHeight="446"/>
	<SubTexture name="Down0002" x="0" y="0" width="417" height="380" frameX="0" frameY="-62" frameWidth="417" frameHeight="446"/>
	<SubTexture name="Down0003" x="417" y="0" width="406" height="370" frameX="-4" frameY="-72" frameWidth="417" frameHeight="446"/>
	<SubTexture name="Down0004" x="417" y="0" width="406" height="370" frameX="-4" frameY="-72" frameWidth="417" frameHeight="446"/>
	<SubTexture name="Down0005" x="417" y="0" width="406" height="370" frameX="-4" frameY="-72" frameWidth="417" frameHeight="446"/>
	<SubTexture name="Down0006" x="823" y="0" width="397" height="380" frameX="-7" frameY="-62" frameWidth="417" frameHeight="446"/>
	<SubTexture name="Down0007" x="823" y="0" width="397" height="380" frameX="-7" frameY="-62" frameWidth="417" frameHeight="446"/>
	<SubTexture name="Down0008" x="823" y="0" width="397" height="380" frameX="-7" frameY="-62" frameWidth="417" frameHeight="446"/>
	<SubTexture name="Down0009" x="1220" y="0" width="395" height="383" frameX="-10" frameY="-60" frameWidth="417" frameHeight="446"/>
	<SubTexture name="Down0010" x="1220" y="0" width="395" height="383" frameX="-10" frameY="-60" frameWidth="417" frameHeight="446"/>
	<SubTexture name="Down0011" x="1220" y="0" width="395" height="383" frameX="-10" frameY="-60" frameWidth="417" frameHeight="446"/>
	<SubTexture name="Down0012" x="1615" y="0" width="393" height="387" frameX="-12" frameY="-57" frameWidth="417" frameHeight="446"/>
	<SubTexture name="Down0013" x="1615" y="0" width="393" height="387" frameX="-12" frameY="-57" frameWidth="417" frameHeight="446"/>
	<SubTexture name="Down0014" x="1615" y="0" width="393" height="387" frameX="-12" frameY="-57" frameWidth="417" frameHeight="446"/>
	<SubTexture name="Down0015" x="2008" y="0" width="393" height="390" frameX="-12" frameY="-54" frameWidth="417" frameHeight="446"/>
	<SubTexture name="Down0016" x="2008" y="0" width="393" height="390" frameX="-12" frameY="-54" frameWidth="417" frameHeight="446"/>
	<SubTexture name="Down0017" x="2008" y="0" width="393" height="390" frameX="-12" frameY="-54" frameWidth="417" frameHeight="446"/>
	<SubTexture name="Down0018" x="2401" y="0" width="393" height="395" frameX="-12" frameY="-49" frameWidth="417" frameHeight="446"/>
	<SubTexture name="Down0019" x="2401" y="0" width="393" height="395" frameX="-12" frameY="-49" frameWidth="417" frameHeight="446"/>
	<SubTexture name="Down0020" x="2401" y="0" width="393" height="395" frameX="-12" frameY="-49" frameWidth="417" frameHeight="446"/>
	<SubTexture name="Down0021" x="2794" y="0" width="394" height="446" frameX="-9" frameY="0" frameWidth="417" frameHeight="446"/>
	<SubTexture name="Down0022" x="2794" y="0" width="394" height="446" frameX="-9" frameY="0" frameWidth="417" frameHeight="446"/>
	<SubTexture name="Idle0000" x="3188" y="0" width="400" height="539" frameX="-1" frameY="-9" frameWidth="402" frameHeight="550"/>
	<SubTexture name="Idle0001" x="3188" y="0" width="400" height="539" frameX="-1" frameY="-9" frameWidth="402" frameHeight="550"/>
	<SubTexture name="Idle0002" x="3588" y="0" width="396" height="541" frameX="-2" frameY="-8" frameWidth="402" frameHeight="550"/>
	<SubTexture name="Idle0003" x="3588" y="0" width="396" height="541" frameX="-2" frameY="-8" frameWidth="402" frameHeight="550"/>
	<SubTexture name="Idle0004" x="3588" y="0" width="396" height="541" frameX="-2" frameY="-8" frameWidth="402" frameHeight="550"/>
	<SubTexture name="Idle0005" x="3588" y="0" width="396" height="541" frameX="-2" frameY="-8" frameWidth="402" frameHeight="550"/>
	<SubTexture name="Idle0006" x="0" y="541" width="393" height="548" frameX="-4" frameY="-2" frameWidth="402" frameHeight="550"/>
	<SubTexture name="Idle0007" x="0" y="541" width="393" height="548" frameX="-4" frameY="-2" frameWidth="402" frameHeight="550"/>
	<SubTexture name="Idle0008" x="0" y="541" width="393" height="548" frameX="-4" frameY="-2" frameWidth="402" frameHeight="550"/>
	<SubTexture name="Idle0009" x="0" y="541" width="393" height="548" frameX="-4" frameY="-2" frameWidth="402" frameHeight="550"/>
	<SubTexture name="Idle0010" x="393" y="541" width="394" height="550" frameX="-6" frameY="0" frameWidth="402" frameHeight="550"/>
	<SubTexture name="Idle0011" x="393" y="541" width="394" height="550" frameX="-6" frameY="0" frameWidth="402" frameHeight="550"/>
	<SubTexture name="Idle0012" x="787" y="541" width="395" height="548" frameX="-5" frameY="-2" frameWidth="402" frameHeight="550"/>
	<SubTexture name="Idle0013" x="787" y="541" width="395" height="548" frameX="-5" frameY="-2" frameWidth="402" frameHeight="550"/>
	<SubTexture name="Idle0014" x="1182" y="541" width="402" height="538" frameX="0" frameY="-11" frameWidth="402" frameHeight="550"/>
	<SubTexture name="Idle0015" x="1182" y="541" width="402" height="538" frameX="0" frameY="-11" frameWidth="402" frameHeight="550"/>
	<SubTexture name="Idle0016" x="1584" y="541" width="394" height="540" frameX="-2" frameY="-9" frameWidth="402" frameHeight="550"/>
	<SubTexture name="Idle0017" x="1584" y="541" width="394" height="540" frameX="-2" frameY="-9" frameWidth="402" frameHeight="550"/>
	<SubTexture name="Idle0018" x="1584" y="541" width="394" height="540" frameX="-2" frameY="-9" frameWidth="402" frameHeight="550"/>
	<SubTexture name="Idle0019" x="1584" y="541" width="394" height="540" frameX="-2" frameY="-9" frameWidth="402" frameHeight="550"/>
	<SubTexture name="Idle0020" x="1978" y="541" width="393" height="546" frameX="-5" frameY="-4" frameWidth="402" frameHeight="550"/>
	<SubTexture name="Idle0021" x="1978" y="541" width="393" height="546" frameX="-5" frameY="-4" frameWidth="402" frameHeight="550"/>
	<SubTexture name="Idle0022" x="1978" y="541" width="393" height="546" frameX="-5" frameY="-4" frameWidth="402" frameHeight="550"/>
	<SubTexture name="Idle0023" x="1978" y="541" width="393" height="546" frameX="-5" frameY="-4" frameWidth="402" frameHeight="550"/>
	<SubTexture name="Idle0024" x="2371" y="541" width="392" height="546" frameX="-6" frameY="-4" frameWidth="402" frameHeight="550"/>
	<SubTexture name="Idle0025" x="2371" y="541" width="392" height="546" frameX="-6" frameY="-4" frameWidth="402" frameHeight="550"/>
	<SubTexture name="Idle0026" x="2763" y="541" width="393" height="545" frameX="-6" frameY="-5" frameWidth="402" frameHeight="550"/>
	<SubTexture name="Idle0027" x="2763" y="541" width="393" height="545" frameX="-6" frameY="-5" frameWidth="402" frameHeight="550"/>
	<SubTexture name="Left0000" x="3156" y="541" width="438" height="474" frameX="0" frameY="-20" frameWidth="466" frameHeight="494"/>
	<SubTexture name="Left0001" x="3156" y="541" width="438" height="474" frameX="0" frameY="-20" frameWidth="466" frameHeight="494"/>
	<SubTexture name="Left0002" x="3156" y="541" width="438" height="474" frameX="0" frameY="-20" frameWidth="466" frameHeight="494"/>
	<SubTexture name="Left0003" x="3594" y="541" width="427" height="463" frameX="-14" frameY="-31" frameWidth="466" frameHeight="494"/>
	<SubTexture name="Left0004" x="3594" y="541" width="427" height="463" frameX="-14" frameY="-31" frameWidth="466" frameHeight="494"/>
	<SubTexture name="Left0005" x="3594" y="541" width="427" height="463" frameX="-14" frameY="-31" frameWidth="466" frameHeight="494"/>
	<SubTexture name="Left0006" x="0" y="1091" width="422" height="466" frameX="-28" frameY="-28" frameWidth="466" frameHeight="494"/>
	<SubTexture name="Left0007" x="0" y="1091" width="422" height="466" frameX="-28" frameY="-28" frameWidth="466" frameHeight="494"/>
	<SubTexture name="Left0008" x="0" y="1091" width="422" height="466" frameX="-28" frameY="-28" frameWidth="466" frameHeight="494"/>
	<SubTexture name="Left0009" x="422" y="1091" width="419" height="467" frameX="-33" frameY="-27" frameWidth="466" frameHeight="494"/>
	<SubTexture name="Left0010" x="422" y="1091" width="419" height="467" frameX="-33" frameY="-27" frameWidth="466" frameHeight="494"/>
	<SubTexture name="Left0011" x="422" y="1091" width="419" height="467" frameX="-33" frameY="-27" frameWidth="466" frameHeight="494"/>
	<SubTexture name="Left0012" x="841" y="1091" width="420" height="465" frameX="-32" frameY="-29" frameWidth="466" frameHeight="494"/>
	<SubTexture name="Left0013" x="841" y="1091" width="420" height="465" frameX="-32" frameY="-29" frameWidth="466" frameHeight="494"/>
	<SubTexture name="Left0014" x="841" y="1091" width="420" height="465" frameX="-32" frameY="-29" frameWidth="466" frameHeight="494"/>
	<SubTexture name="Left0015" x="841" y="1091" width="420" height="465" frameX="-32" frameY="-29" frameWidth="466" frameHeight="494"/>
	<SubTexture name="Left0016" x="841" y="1091" width="420" height="465" frameX="-32" frameY="-29" frameWidth="466" frameHeight="494"/>
	<SubTexture name="Left0017" x="841" y="1091" width="420" height="465" frameX="-32" frameY="-29" frameWidth="466" frameHeight="494"/>
	<SubTexture name="Left0018" x="1261" y="1091" width="410" height="472" frameX="-44" frameY="-22" frameWidth="466" frameHeight="494"/>
	<SubTexture name="Left0019" x="1261" y="1091" width="410" height="472" frameX="-44" frameY="-22" frameWidth="466" frameHeight="494"/>
	<SubTexture name="Left0020" x="1261" y="1091" width="410" height="472" frameX="-44" frameY="-22" frameWidth="466" frameHeight="494"/>
	<SubTexture name="Left0021" x="1671" y="1091" width="403" height="494" frameX="-63" frameY="0" frameWidth="466" frameHeight="494"/>
	<SubTexture name="Left0022" x="1671" y="1091" width="403" height="494" frameX="-63" frameY="0" frameWidth="466" frameHeight="494"/>
	<SubTexture name="Left0023" x="1671" y="1091" width="403" height="494" frameX="-63" frameY="0" frameWidth="466" frameHeight="494"/>
	<SubTexture name="Right0000" x="2074" y="1091" width="510" height="526" frameX="-1" frameY="-12" frameWidth="511" frameHeight="538"/>
	<SubTexture name="Right0001" x="2074" y="1091" width="510" height="526" frameX="-1" frameY="-12" frameWidth="511" frameHeight="538"/>
	<SubTexture name="Right0002" x="2074" y="1091" width="510" height="526" frameX="-1" frameY="-12" frameWidth="511" frameHeight="538"/>
	<SubTexture name="Right0003" x="2584" y="1091" width="493" height="531" frameX="-1" frameY="-7" frameWidth="511" frameHeight="538"/>
	<SubTexture name="Right0004" x="2584" y="1091" width="493" height="531" frameX="-1" frameY="-7" frameWidth="511" frameHeight="538"/>
	<SubTexture name="Right0005" x="2584" y="1091" width="493" height="531" frameX="-1" frameY="-7" frameWidth="511" frameHeight="538"/>
	<SubTexture name="Right0006" x="3077" y="1091" width="483" height="537" frameX="-1" frameY="-1" frameWidth="511" frameHeight="538"/>
	<SubTexture name="Right0007" x="3077" y="1091" width="483" height="537" frameX="-1" frameY="-1" frameWidth="511" frameHeight="538"/>
	<SubTexture name="Right0008" x="3077" y="1091" width="483" height="537" frameX="-1" frameY="-1" frameWidth="511" frameHeight="538"/>
	<SubTexture name="Right0009" x="3560" y="1091" width="482" height="538" frameX="-1" frameY="0" frameWidth="511" frameHeight="538"/>
	<SubTexture name="Right0010" x="3560" y="1091" width="482" height="538" frameX="-1" frameY="0" frameWidth="511" frameHeight="538"/>
	<SubTexture name="Right0011" x="3560" y="1091" width="482" height="538" frameX="-1" frameY="0" frameWidth="511" frameHeight="538"/>
	<SubTexture name="Right0012" x="0" y="1629" width="482" height="538" frameX="-1" frameY="0" frameWidth="511" frameHeight="538"/>
	<SubTexture name="Right0013" x="0" y="1629" width="482" height="538" frameX="-1" frameY="0" frameWidth="511" frameHeight="538"/>
	<SubTexture name="Right0014" x="0" y="1629" width="482" height="538" frameX="-1" frameY="0" frameWidth="511" frameHeight="538"/>
	<SubTexture name="Right0015" x="482" y="1629" width="482" height="537" frameX="-1" frameY="-1" frameWidth="511" frameHeight="538"/>
	<SubTexture name="Right0016" x="482" y="1629" width="482" height="537" frameX="-1" frameY="-1" frameWidth="511" frameHeight="538"/>
	<SubTexture name="Right0017" x="482" y="1629" width="482" height="537" frameX="-1" frameY="-1" frameWidth="511" frameHeight="538"/>
	<SubTexture name="Right0018" x="964" y="1629" width="481" height="538" frameX="0" frameY="0" frameWidth="511" frameHeight="538"/>
	<SubTexture name="Right0019" x="964" y="1629" width="481" height="538" frameX="0" frameY="0" frameWidth="511" frameHeight="538"/>
	<SubTexture name="Right0020" x="964" y="1629" width="481" height="538" frameX="0" frameY="0" frameWidth="511" frameHeight="538"/>
	<SubTexture name="Up0000" x="1445" y="1629" width="461" height="651" frameX="-21" frameY="0" frameWidth="486" frameHeight="651"/>
	<SubTexture name="Up0001" x="1445" y="1629" width="461" height="651" frameX="-21" frameY="0" frameWidth="486" frameHeight="651"/>
	<SubTexture name="Up0002" x="1906" y="1629" width="461" height="651" frameX="-21" frameY="0" frameWidth="486" frameHeight="651"/>
	<SubTexture name="Up0003" x="1906" y="1629" width="461" height="651" frameX="-21" frameY="0" frameWidth="486" frameHeight="651"/>
	<SubTexture name="Up0004" x="2367" y="1629" width="477" height="631" frameX="-8" frameY="-19" frameWidth="486" frameHeight="651"/>
	<SubTexture name="Up0005" x="2367" y="1629" width="477" height="631" frameX="-8" frameY="-19" frameWidth="486" frameHeight="651"/>
	<SubTexture name="Up0006" x="2367" y="1629" width="477" height="631" frameX="-8" frameY="-19" frameWidth="486" frameHeight="651"/>
	<SubTexture name="Up0007" x="2844" y="1629" width="483" height="621" frameX="-3" frameY="-29" frameWidth="486" frameHeight="651"/>
	<SubTexture name="Up0008" x="2844" y="1629" width="483" height="621" frameX="-3" frameY="-29" frameWidth="486" frameHeight="651"/>
	<SubTexture name="Up0009" x="2844" y="1629" width="483" height="621" frameX="-3" frameY="-29" frameWidth="486" frameHeight="651"/>
	<SubTexture name="Up0010" x="3327" y="1629" width="483" height="618" frameX="-3" frameY="-32" frameWidth="486" frameHeight="651"/>
	<SubTexture name="Up0011" x="3327" y="1629" width="483" height="618" frameX="-3" frameY="-32" frameWidth="486" frameHeight="651"/>
	<SubTexture name="Up0012" x="3327" y="1629" width="483" height="618" frameX="-3" frameY="-32" frameWidth="486" frameHeight="651"/>
	<SubTexture name="Up0013" x="0" y="2280" width="483" height="618" frameX="-3" frameY="-32" frameWidth="486" frameHeight="651"/>
	<SubTexture name="Up0014" x="0" y="2280" width="483" height="618" frameX="-3" frameY="-32" frameWidth="486" frameHeight="651"/>
	<SubTexture name="Up0015" x="0" y="2280" width="483" height="618" frameX="-3" frameY="-32" frameWidth="486" frameHeight="651"/>
	<SubTexture name="Up0016" x="483" y="2280" width="482" height="618" frameX="-3" frameY="-32" frameWidth="486" frameHeight="651"/>
	<SubTexture name="Up0017" x="483" y="2280" width="482" height="618" frameX="-3" frameY="-32" frameWidth="486" frameHeight="651"/>
	<SubTexture name="Up0018" x="483" y="2280" width="482" height="618" frameX="-3" frameY="-32" frameWidth="486" frameHeight="651"/>
	<SubTexture name="Up0019" x="965" y="2280" width="483" height="611" frameX="0" frameY="-40" frameWidth="486" frameHeight="651"/>
	<SubTexture name="Up0020" x="965" y="2280" width="483" height="611" frameX="0" frameY="-40" frameWidth="486" frameHeight="651"/>
</TextureAtlas>
